{
  "name": "273",
  "description": "Welcome to Kami World, a vibrant and enchanted realm! A collection of 1000 Kamis all hand made and created in blender! Explore the Kamiverse and enjoy your stay at the Citadel.",
  "image": "https://gateway.pinata.cloud/ipfs/QmNcP6JjWsqv4UN95n6a7cNMYU5ynZRMAZJeWLP6A2fo2C",
  "attributes": {
    "Race": "Sentinel",
    "Skin": "PinkDiamond",
    "Eyes": "Omniscient",
    "Enchanted Tool": "None",
    "Dye": "GlimmerRed",
    "Garments": "MajesticGuard",
    "Background": "Souls"
  }
}